[{"url":"/2005/09/25/lighttpd-working.html","title":"Lighttpd Working","tags":["post:tags=rails","post:tags=lighttpd","post:type=tutorial"]},{"url":"/2005/10/01/multiple-databases-on-rails.html","title":"Multiple Databases On Rails","tags":["gem:name=activerecord","gem:tags=rails","post:lang=ruby","post:type=snippet"]},{"url":"/2005/10/08/irb-history-itches-eliminated.html","title":"Irb History Itches Eliminated","tags":["lib:name=irb","post:type=snippet","post:lang=ruby"]},{"url":"/2005/11/14/rails-overview-with-rdoc-parser.html","title":"Rails Overview With Rdoc Parser","tags":["post:type=snippet","post:lang=ruby","lib:name=rdoc","lib:topic=parse","post:tags=rails"]},{"url":"/2008/12/17/tags-trees-facets-oh-my.html","title":"Tags Trees Facets Oh My","tags":["post:tags=tag","post:type=thoughts"]},{"url":"/2009/01/21/block-to-hash-conversion-ruby.html","title":"Block To Hash Conversion Ruby","tags":["lib:name=ostruct","lib:topic=block","post:type=tutorial","post:lang=ruby"]},{"url":"/2009/01/31/share-extensions-without-monkey-patching.html","title":"Share Extensions Without Monkey Patching","tags":["gem:topic=monkeypatch","gem:name=activesupport","gem:tags=rails","post:lang=ruby","post:type=thoughts"]},{"url":"/2009/02/05/local-gem-loads-your-current-code-now.html","title":"Local Gem Loads Your Current Code Now","tags":["gem:name=local_gem","post:lang=ruby","post:type=tutorial"]},{"url":"/2009/02/15/goodbye-blogger-hello-github-pages.html","title":"Goodbye Blogger Hello Github Pages","tags":["post:site=github","post:type=thoughts"]},{"url":"/2009/02/19/meta-templates-for-github-pages.html","title":"Meta Templates For Github Pages","tags":["post:site=github","gem:name=jekyll","gem:name=thor","gem:topic=template","post:lang=ruby","post:type=tutorial"]},{"url":"/2009/02/23/quicker-options-for-irb-methods.html","title":"Quicker Options For Irb Methods","tags":["gem:name=thor","lib:name=irb","post:type=tutorial","gem:topic=parse","gem:topic=options","post:lang=ruby"]},{"url":"/2009/02/28/Console-Update-With-Your-Editor.html","title":"Console Update With Your Editor","tags":["gem:name=activerecord","lib:name=irb","gem:name=console_update","gem:topic=database","post:type=tutorial","post:lang=ruby"]},{"url":"/2009/03/13/hirb-irb-on-the-good-stuff.html","title":"Hirb Irb On The Good Stuff","tags":["gem:name=hirb","lib:name=irb","gem:name=activerecord","gem:tags=rails","gem:topic=table","post:lang=ruby","post:type=tutorial"]},{"url":"/2009/03/18/ruby-class-trees-rails-plugin-trees-with-hirb.html","title":"Ruby Class Trees Rails Plugin Trees With Hirb","tags":["gem:name=hirb","lib:name=irb","gem:name=activerecord","gem:tags=rails","lib:plugin=acts_as_tree","gem:topic=tree","post:lang=ruby","post:type=tutorial"]},{"url":"/2009/03/26/what-are-machine-tags.html","title":"What Are Machine Tags","tags":["post:tags=tag","post:type=tutorial"]},{"url":"/2009/04/06/github-bookmarklet-for-user-pages.html","title":"Github Bookmarklet For User Pages","tags":["post:site=github","post:type=snippet","post:lang=javascript","post:tags=jquery"]},{"url":"/2009/04/08/building-dry-gems-with-thor-and-jeweler.html","title":"Building Dry Gems With Thor And Jeweler","tags":["post:lang=ruby","post:type=tutorial","gem:name=thor","gem:name=jeweler"]},{"url":"/2009/04/14/i-am-machine-tag-and-so-can-you.html","title":"I Am Machine Tag And So Can You","tags":["post:tags=tag","post:lang=javascript","post:type=tutorial","post:tags=jquery"]},{"url":"/2009/04/23/how-to-write-a-rubygem-command-plugin.html","title":"How To Write A Rubygem Command Plugin","tags":["post:type=tutorial","post:lang=ruby","post:tags=gems","gem:name=gem_grep"]},{"url":"/2009/04/26/machine-tagging-with-delicious.html","title":"Machine Tagging With Delicious","tags":["post:lang=javascript","post:tags=jquery","post:tags=tag","post:type=tutorial","post:site=delicious"]},{"url":"/2009/05/11/demystifying-irb-commands.html","title":"Demystifying Irb Commands","tags":["lib:name=irb","post:type=tutorial","post:lang=ruby"]},{"url":"/2009/05/29/exploring-how-to-configure-irb.html","title":"Exploring How To Configure Irb","tags":["lib:name=irb","post:type=tutorial","post:lang=ruby"]},{"url":"/2009/06/19/page-irb-output-and-improve-ri-with-hirb.html","title":"Page Irb Output And Improve Ri With Hirb","tags":["gem:name=hirb","lib:name=irb","lib:name=ri","post:lang=ruby","post:type=tutorial"]},{"url":"/2009/07/07/alias-quickness-in-the-ruby-console.html","title":"Alias Quickness In The Ruby Console","tags":["gem:name=alias","gem:tags=rails","lib:name=irb","post:lang=ruby","post:type=tutorial"]},{"url":"/2009/07/16/bond-from-irb-with-completion-love.html","title":"Bond From Irb With Completion Love","tags":["gem:name=bond","lib:name=irb","post:topic=completion","post:lang=ruby","post:type=tutorial"]},{"url":"/2009/07/22/better-irb-completion-with-bond.html","title":"Better Irb Completion With Bond","tags":["gem:name=bond","lib:name=irb","post:lang=ruby","post:type=tutorial"]},{"url":"/2009/07/23/mini-irb-and-mini-script-console.html","title":"Mini Irb And Mini Script Console","tags":["gem:name=bond","lib:name=irb","post:topic=completion","post:lang=ruby","post:type=snippet"]},{"url":"/2009/07/30/changing-readline-completions-with-key-combo.html","title":"Changing Readline Completions With Key Combo","tags":["gem:name=bond","lib:name=irb","post:topic=completion","post:lang=ruby","post:type=tutorial"]},{"url":"/2009/09/07/hirb-tips-for-rails.html","title":"Hirb Tips For Rails","tags":["gem:name=hirb","gem:tags=rails","post:type=snippet","post:lang=ruby"]},{"url":"/2009/10/14/boson-command-your-ruby-universe.html","title":"Boson Command Your Ruby Universe","tags":["gem:name=boson","gem:topic=options","lib:name=irb","post:lang=ruby","post:type=tutorial"]},{"url":"/2009/10/15/boson-and-hirb-interactions.html","title":"Boson And Hirb Interactions","tags":["gem:name=boson","gem:name=hirb","gem:topic=options","lib:name=irb","post:lang=ruby","post:type=tutorial"]},{"url":"/2009/10/19/how-boson-enhances-your-irb-experience.html","title":"How Boson Enhances Your Irb Experience","tags":["gem:name=boson","lib:name=irb","post:lang=ruby","post:type=tutorial"]},{"url":"/2009/11/07/ruby-reference-commands-with-boson.html","title":"Ruby Reference Commands With Boson","tags":["gem:name=boson","lib:name=irb","post:lang=ruby","post:type=tutorial"]},{"url":"/2009/11/21/boson-command-your-ruby-universe-part-deux.html","title":"Boson Command Your Ruby Universe Part Deux","tags":["gem:name=boson","lib:name=irb","post:lang=ruby","post:type=tutorial"]},{"url":"/2010/01/26/typing-less-in-irb-with-method_missing.html","title":"Typing Less In Irb With Method_missing","tags":["post:method=method_missing","post:type=snippet","post:lang=ruby","lib:name=irb"]},{"url":"/2010/02/03/using-gemcutters-api-from-the-commandline.html","title":"Using Gemcutters Api From The Commandline","tags":["post:type=tutorial","post:lang=ruby","post:site=gemcutter","gem:topic=api","gem:name=boson"]},{"url":"/2010/02/16/two-dimensional-console-menus-with-hirb.html","title":"Two Dimensional Console Menus With Hirb","tags":["post:type=tutorial","post:lang=ruby","gem:name=hirb","gem:name=boson","gem:topic=menu"]}]